{
  "__type__": "cc.AnimationClip",
  "_name": "startOrStop",
  "_duration": 1.15,
  "curveData": {
    "props": {
      "skewX": [
        {
          "frame": 0.08333333333333333,
          "value": -30
        },
        {
          "frame": 0.5833333333333334,
          "value": 20
        },
        {
          "frame": 0.8,
          "value": 0
        }
      ],
      "opacity": [
        {
          "frame": 0,
          "value": 20
        },
        {
          "frame": 0.18333333333333332,
          "value": 120
        },
        {
          "frame": 0.48333333333333334,
          "value": 200
        },
        {
          "frame": 0.8,
          "value": 255
        }
      ],
      "position": [
        {
          "frame": 0,
          "value": [
            -120,
            39
          ]
        },
        {
          "frame": 0.38333333333333336,
          "value": [
            0,
            39
          ]
        },
        {
          "frame": 0.5,
          "value": [
            60,
            39
          ]
        },
        {
          "frame": 0.8,
          "value": [
            0,
            39
          ]
        }
      ]
    }
  },
  "events": [
    {
      "frame": 1.15,
      "func": "hideAction",
      "params": [
        false
      ]
    }
  ]
}